<annotation>
	<folder>images</folder>
	<filename>bear_99.jpg</filename>
	<path>C:\Users\jbansal\Documents\GitHub\computer-vision-demos\images\bear_99.jpg</path>
	<source>
		<database>Unknown</database>
	</source>
	<size>
		<width>800</width>
		<height>450</height>
		<depth>3</depth>
	</size>
	<segmented>0</segmented>
	<object>
		<name>bear</name>
		<pose>Unspecified</pose>
		<truncated>0</truncated>
		<difficult>0</difficult>
		<bndbox>
			<xmin>16</xmin>
			<ymin>2</ymin>
			<xmax>452</xmax>
			<ymax>405</ymax>
		</bndbox>
	</object>
</annotation>
